{
  "annotations": {
    "list": [
      {
        "builtIn": 1,
        "datasource": "-- Grafana --",
        "enable": true,
        "hide": true,
        "iconColor": "rgba(0, 211, 255, 1)",
        "name": "Annotations & Alerts",
        "type": "dashboard"
      }
    ]
  },
  "editable": true,
  "gnetId": null,
  "graphTooltip": 0,
  "links": [],
  "panels": [
    {
      "collapsed": false,
      "datasource": null,
      "gridPos": {
        "h": 1,
        "w": 24,
        "x": 0,
        "y": 0
      },
      "id": 26,
      "panels": [],
      "title": "Uptime Metrics",
      "type": "row"
    },
    {
      "content": "<br/>\n<center>\n  <a href=\"https://github.com/ewohltman/ephemeral-roles\"><img src=\"https://github.com/ewohltman/ephemeral-roles/raw/master/web/static/Testa_Anatomica-Filippo_Balbi.jpg\" width=\"50\"></a>\n  &nbsp\n  <a href=\"https://github.com/ewohltman/ephemeral-roles\">ephemeral-roles</a>\n</center>",
      "datasource": null,
      "fieldConfig": {
        "defaults": {
          "custom": {}
        },
        "overrides": []
      },
      "gridPos": {
        "h": 3,
        "w": 3,
        "x": 0,
        "y": 1
      },
      "id": 20,
      "links": [],
      "mode": "html",
      "options": {
        "content": "<br/>\n<center>\n  <a href=\"https://github.com/ewohltman/ephemeral-roles\"><img src=\"https://github.com/ewohltman/ephemeral-roles/raw/master/web/static/Testa_Anatomica-Filippo_Balbi.jpg\" width=\"50\"></a>\n  &nbsp\n  <a href=\"https://github.com/ewohltman/ephemeral-roles\">ephemeral-roles</a>\n</center>",
        "mode": "html"
      },
      "pluginVersion": "7.1.0",
      "title": "",
      "type": "text"
    },
    {
      "aliasColors": {},
      "bars": false,
      "dashLength": 10,
      "dashes": false,
      "datasource": "prometheus",
      "fieldConfig": {
        "defaults": {
          "custom": {},
          "links": []
        },
        "overrides": []
      },
      "fill": 3,
      "fillGradient": 0,
      "gridPos": {
        "h": 3,
        "w": 21,
        "x": 3,
        "y": 1
      },
      "hiddenSeries": false,
      "id": 14,
      "legend": {
        "avg": false,
        "current": false,
        "max": false,
        "min": false,
        "show": false,
        "total": false,
        "values": false
      },
      "lines": true,
      "linewidth": 2,
      "links": [],
      "nullPointMode": "null",
      "percentage": false,
      "pluginVersion": "7.1.0",
      "pointradius": 5,
      "points": false,
      "renderer": "flot",
      "seriesOverrides": [
        {
          "alias": "uptime",
          "color": "#37872D",
          "fill": 2
        }
      ],
      "spaceLength": 10,
      "stack": false,
      "steppedLine": false,
      "targets": [
        {
          "expr": "avg(label_replace(up{namespace=\"ephemeral-roles\",service=\"ephemeral-roles\"}, \"instance\", \"\", \"instance\", \".+\"))",
          "format": "time_series",
          "intervalFactor": 1,
          "legendFormat": "uptime",
          "refId": "A"
        }
      ],
      "thresholds": [],
      "timeFrom": null,
      "timeRegions": [],
      "timeShift": null,
      "title": "Bot Uptime",
      "tooltip": {
        "shared": true,
        "sort": 0,
        "value_type": "individual"
      },
      "type": "graph",
      "xaxis": {
        "buckets": null,
        "mode": "time",
        "name": null,
        "show": true,
        "values": []
      },
      "yaxes": [
        {
          "decimals": 0,
          "format": "short",
          "label": null,
          "logBase": 1,
          "max": "1",
          "min": "0",
          "show": false
        },
        {
          "format": "short",
          "label": null,
          "logBase": 1,
          "max": null,
          "min": null,
          "show": false
        }
      ],
      "yaxis": {
        "align": false,
        "alignLevel": null
      }
    },
    {
      "collapsed": false,
      "datasource": null,
      "gridPos": {
        "h": 1,
        "w": 24,
        "x": 0,
        "y": 4
      },
      "id": 28,
      "panels": [],
      "title": "Usage Metrics",
      "type": "row"
    },
    {
      "aliasColors": {},
      "bars": false,
      "dashLength": 10,
      "dashes": false,
      "datasource": "prometheus",
      "decimals": 0,
      "fieldConfig": {
        "defaults": {
          "custom": {},
          "links": []
        },
        "overrides": []
      },
      "fill": 1,
      "fillGradient": 0,
      "gridPos": {
        "h": 6,
        "w": 12,
        "x": 0,
        "y": 5
      },
      "hiddenSeries": false,
      "id": 30,
      "legend": {
        "alignAsTable": true,
        "avg": false,
        "current": true,
        "max": false,
        "min": false,
        "show": true,
        "total": false,
        "values": true
      },
      "lines": true,
      "linewidth": 1,
      "links": [],
      "nullPointMode": "null",
      "percentage": false,
      "pluginVersion": "7.1.0",
      "pointradius": 5,
      "points": false,
      "renderer": "flot",
      "seriesOverrides": [
        {
          "alias": "servers",
          "color": "#C4162A"
        }
      ],
      "spaceLength": 10,
      "stack": false,
      "steppedLine": false,
      "targets": [
        {
          "expr": "sum(label_replace(ephemeral_roles_guilds_count, \"instance\", \"\", \"instance\", \".+\"))",
          "format": "time_series",
          "intervalFactor": 1,
          "legendFormat": "servers",
          "refId": "A"
        }
      ],
      "thresholds": [],
      "timeFrom": null,
      "timeRegions": [],
      "timeShift": null,
      "title": "Bot Servers",
      "tooltip": {
        "shared": true,
        "sort": 0,
        "value_type": "individual"
      },
      "type": "graph",
      "xaxis": {
        "buckets": null,
        "mode": "time",
        "name": null,
        "show": true,
        "values": []
      },
      "yaxes": [
        {
          "decimals": 0,
          "format": "short",
          "label": null,
          "logBase": 1,
          "max": null,
          "min": null,
          "show": true
        },
        {
          "format": "short",
          "label": null,
          "logBase": 1,
          "max": null,
          "min": null,
          "show": false
        }
      ],
      "yaxis": {
        "align": false,
        "alignLevel": null
      }
    },
    {
      "datasource": "prometheus",
      "fieldConfig": {
        "defaults": {
          "custom": {},
          "displayName": "",
          "mappings": [],
          "thresholds": {
            "mode": "absolute",
            "steps": [
              {
                "color": "semi-dark-red",
                "value": null
              }
            ]
          }
        },
        "overrides": []
      },
      "gridPos": {
        "h": 6,
        "w": 12,
        "x": 12,
        "y": 5
      },
      "id": 44,
      "options": {
        "displayMode": "lcd",
        "orientation": "horizontal",
        "reduceOptions": {
          "calcs": [
            "last"
          ],
          "fields": "",
          "values": false
        },
        "showUnfilled": true
      },
      "pluginVersion": "7.1.0",
      "targets": [
        {
          "expr": "label_replace(ephemeral_roles_guilds_count{pod=~\"ephemeral-roles-.+\"}, \"instance\", \"\", \"instance\", \".+\")",
          "legendFormat": "{{pod}}",
          "refId": "A"
        }
      ],
      "timeFrom": null,
      "timeShift": null,
      "title": "Bot Server Distribution",
      "type": "bargauge"
    },
    {
      "aliasColors": {},
      "bars": false,
      "dashLength": 10,
      "dashes": false,
      "datasource": "prometheus",
      "decimals": 0,
      "fieldConfig": {
        "defaults": {
          "custom": {},
          "links": []
        },
        "overrides": []
      },
      "fill": 1,
      "fillGradient": 0,
      "gridPos": {
        "h": 6,
        "w": 12,
        "x": 0,
        "y": 11
      },
      "hiddenSeries": false,
      "id": 32,
      "legend": {
        "alignAsTable": true,
        "avg": false,
        "current": true,
        "max": false,
        "min": false,
        "rightSide": false,
        "show": true,
        "total": false,
        "values": true
      },
      "lines": true,
      "linewidth": 1,
      "links": [],
      "nullPointMode": "null",
      "percentage": false,
      "pluginVersion": "7.1.0",
      "pointradius": 5,
      "points": false,
      "renderer": "flot",
      "seriesOverrides": [
        {
          "alias": "users",
          "color": "#C4162A"
        }
      ],
      "spaceLength": 10,
      "stack": false,
      "steppedLine": false,
      "targets": [
        {
          "expr": "sum(label_replace(ephemeral_roles_members_count, \"instance\", \"\", \"instance\", \".+\"))",
          "format": "time_series",
          "intervalFactor": 1,
          "legendFormat": "users",
          "refId": "A"
        }
      ],
      "thresholds": [],
      "timeFrom": null,
      "timeRegions": [],
      "timeShift": null,
      "title": "Bot Users",
      "tooltip": {
        "shared": true,
        "sort": 0,
        "value_type": "individual"
      },
      "type": "graph",
      "xaxis": {
        "buckets": null,
        "mode": "time",
        "name": null,
        "show": true,
        "values": []
      },
      "yaxes": [
        {
          "decimals": 0,
          "format": "none",
          "label": null,
          "logBase": 1,
          "max": null,
          "min": null,
          "show": true
        },
        {
          "format": "short",
          "label": null,
          "logBase": 1,
          "max": null,
          "min": null,
          "show": false
        }
      ],
      "yaxis": {
        "align": false,
        "alignLevel": null
      }
    },
    {
      "datasource": "prometheus",
      "fieldConfig": {
        "defaults": {
          "custom": {},
          "mappings": [],
          "thresholds": {
            "mode": "absolute",
            "steps": [
              {
                "color": "semi-dark-red",
                "value": null
              }
            ]
          }
        },
        "overrides": []
      },
      "gridPos": {
        "h": 6,
        "w": 12,
        "x": 12,
        "y": 11
      },
      "id": 46,
      "options": {
        "displayMode": "lcd",
        "orientation": "horizontal",
        "reduceOptions": {
          "calcs": [
            "last"
          ],
          "fields": "",
          "values": false
        },
        "showUnfilled": true
      },
      "pluginVersion": "7.1.0",
      "targets": [
        {
          "expr": "label_replace(ephemeral_roles_members_count{pod=~\"ephemeral-roles-.+\"}, \"instance\", \"\", \"instance\", \".+\")",
          "legendFormat": "{{pod}}",
          "refId": "A"
        }
      ],
      "timeFrom": null,
      "timeShift": null,
      "title": "Bot Users Distribution",
      "type": "bargauge"
    },
    {
      "collapsed": false,
      "datasource": null,
      "gridPos": {
        "h": 1,
        "w": 24,
        "x": 0,
        "y": 17
      },
      "id": 24,
      "panels": [],
      "title": "Discord Event Metrics",
      "type": "row"
    },
    {
      "aliasColors": {},
      "bars": false,
      "dashLength": 10,
      "dashes": false,
      "datasource": "prometheus",
      "fieldConfig": {
        "defaults": {
          "custom": {},
          "links": []
        },
        "overrides": []
      },
      "fill": 1,
      "fillGradient": 0,
      "gridPos": {
        "h": 6,
        "w": 12,
        "x": 0,
        "y": 18
      },
      "hiddenSeries": false,
      "id": 12,
      "legend": {
        "alignAsTable": true,
        "avg": true,
        "current": true,
        "max": false,
        "min": false,
        "show": true,
        "total": false,
        "values": true
      },
      "lines": true,
      "linewidth": 1,
      "links": [],
      "nullPointMode": "null",
      "percentage": false,
      "pluginVersion": "7.1.0",
      "pointradius": 5,
      "points": false,
      "renderer": "flot",
      "seriesOverrides": [
        {
          "alias": "events/second",
          "color": "#8F3BB8"
        }
      ],
      "spaceLength": 10,
      "stack": false,
      "steppedLine": false,
      "targets": [
        {
          "expr": "sum(label_replace(irate(ephemeral_roles_message_create_events[1m]), \"instance\", \"\", \"instance\", \".+\"))",
          "format": "time_series",
          "intervalFactor": 1,
          "legendFormat": "events/second",
          "refId": "A"
        }
      ],
      "thresholds": [],
      "timeFrom": null,
      "timeRegions": [],
      "timeShift": null,
      "title": "MessageCreate - Events Per Second",
      "tooltip": {
        "shared": true,
        "sort": 0,
        "value_type": "individual"
      },
      "type": "graph",
      "xaxis": {
        "buckets": null,
        "mode": "time",
        "name": null,
        "show": true,
        "values": []
      },
      "yaxes": [
        {
          "decimals": 0,
          "format": "short",
          "label": null,
          "logBase": 1,
          "max": null,
          "min": null,
          "show": true
        },
        {
          "format": "short",
          "label": null,
          "logBase": 1,
          "max": null,
          "min": null,
          "show": false
        }
      ],
      "yaxis": {
        "align": false,
        "alignLevel": null
      }
    },
    {
      "aliasColors": {},
      "bars": false,
      "dashLength": 10,
      "dashes": false,
      "datasource": "prometheus",
      "fieldConfig": {
        "defaults": {
          "custom": {},
          "links": []
        },
        "overrides": []
      },
      "fill": 1,
      "fillGradient": 0,
      "gridPos": {
        "h": 6,
        "w": 12,
        "x": 12,
        "y": 18
      },
      "hiddenSeries": false,
      "id": 10,
      "legend": {
        "alignAsTable": true,
        "avg": true,
        "current": true,
        "max": false,
        "min": false,
        "show": true,
        "total": false,
        "values": true
      },
      "lines": true,
      "linewidth": 1,
      "links": [],
      "nullPointMode": "null",
      "percentage": false,
      "pluginVersion": "7.1.0",
      "pointradius": 5,
      "points": false,
      "renderer": "flot",
      "seriesOverrides": [
        {
          "alias": "events/second",
          "color": "#8F3BB8"
        }
      ],
      "spaceLength": 10,
      "stack": false,
      "steppedLine": false,
      "targets": [
        {
          "expr": "sum(label_replace(irate(ephemeral_roles_voice_state_update_events[1m]), \"instance\", \"\", \"instance\", \".+\"))",
          "format": "time_series",
          "intervalFactor": 1,
          "legendFormat": "events/second",
          "refId": "A"
        }
      ],
      "thresholds": [],
      "timeFrom": null,
      "timeRegions": [],
      "timeShift": null,
      "title": "VoiceStateUpdate - Events Per Second",
      "tooltip": {
        "shared": true,
        "sort": 0,
        "value_type": "individual"
      },
      "type": "graph",
      "xaxis": {
        "buckets": null,
        "mode": "time",
        "name": null,
        "show": true,
        "values": []
      },
      "yaxes": [
        {
          "decimals": 0,
          "format": "short",
          "label": null,
          "logBase": 1,
          "max": null,
          "min": null,
          "show": true
        },
        {
          "format": "short",
          "label": null,
          "logBase": 1,
          "max": null,
          "min": null,
          "show": false
        }
      ],
      "yaxis": {
        "align": false,
        "alignLevel": null
      }
    },
    {
      "collapsed": false,
      "datasource": null,
      "gridPos": {
        "h": 1,
        "w": 24,
        "x": 0,
        "y": 24
      },
      "id": 22,
      "panels": [],
      "title": "Performance Metrics",
      "type": "row"
    },
    {
      "aliasColors": {},
      "bars": false,
      "dashLength": 10,
      "dashes": false,
      "datasource": "prometheus",
      "decimals": 0,
      "fieldConfig": {
        "defaults": {
          "custom": {},
          "links": []
        },
        "overrides": []
      },
      "fill": 1,
      "fillGradient": 0,
      "gridPos": {
        "h": 11,
        "w": 12,
        "x": 0,
        "y": 25
      },
      "hiddenSeries": false,
      "id": 2,
      "legend": {
        "alignAsTable": true,
        "avg": true,
        "current": true,
        "max": false,
        "min": false,
        "rightSide": false,
        "show": true,
        "sort": "current",
        "sortDesc": true,
        "total": false,
        "values": true
      },
      "lines": true,
      "linewidth": 1,
      "links": [],
      "nullPointMode": "null",
      "percentage": false,
      "pluginVersion": "7.1.0",
      "pointradius": 5,
      "points": false,
      "renderer": "flot",
      "seriesOverrides": [
        {
          "$$hashKey": "object:68",
          "alias": "/ephemeral-roles/",
          "color": "#1F60C4",
          "linewidth": 2
        }
      ],
      "spaceLength": 10,
      "stack": false,
      "steppedLine": false,
      "targets": [
        {
          "expr": "label_replace(process_resident_memory_bytes{pod=~\"ephemeral-roles.+\"}, \"instance\", \"\", \"instance\", \".+\")",
          "interval": "",
          "legendFormat": "{{pod}}",
          "refId": "A"
        }
      ],
      "thresholds": [
        {
          "$$hashKey": "object:113",
          "colorMode": "critical",
          "fill": false,
          "line": true,
          "op": "lt",
          "value": 268435456,
          "yaxis": "left"
        }
      ],
      "timeFrom": null,
      "timeRegions": [],
      "timeShift": null,
      "title": "RES Memory Usage",
      "tooltip": {
        "shared": true,
        "sort": 2,
        "value_type": "individual"
      },
      "type": "graph",
      "xaxis": {
        "buckets": null,
        "mode": "time",
        "name": null,
        "show": true,
        "values": []
      },
      "yaxes": [
        {
          "$$hashKey": "object:170",
          "decimals": 0,
          "format": "bytes",
          "label": null,
          "logBase": 2,
          "max": "268435456",
          "min": null,
          "show": true
        },
        {
          "$$hashKey": "object:171",
          "format": "bytes",
          "label": null,
          "logBase": 1,
          "max": null,
          "min": null,
          "show": false
        }
      ],
      "yaxis": {
        "align": false,
        "alignLevel": null
      }
    },
    {
      "aliasColors": {},
      "bars": false,
      "dashLength": 10,
      "dashes": false,
      "datasource": "prometheus",
      "decimals": 0,
      "fieldConfig": {
        "defaults": {
          "custom": {},
          "links": []
        },
        "overrides": []
      },
      "fill": 1,
      "fillGradient": 0,
      "gridPos": {
        "h": 11,
        "w": 12,
        "x": 12,
        "y": 25
      },
      "hiddenSeries": false,
      "id": 42,
      "legend": {
        "alignAsTable": true,
        "avg": true,
        "current": true,
        "max": false,
        "min": false,
        "show": true,
        "sort": "current",
        "sortDesc": true,
        "total": false,
        "values": true
      },
      "lines": true,
      "linewidth": 1,
      "links": [],
      "nullPointMode": "null",
      "percentage": false,
      "pluginVersion": "7.1.0",
      "pointradius": 5,
      "points": false,
      "renderer": "flot",
      "seriesOverrides": [
        {
          "$$hashKey": "object:661",
          "alias": "/ephemeral-roles/",
          "color": "#FA6400",
          "linewidth": 2
        }
      ],
      "spaceLength": 10,
      "stack": false,
      "steppedLine": false,
      "targets": [
        {
          "expr": "label_replace(go_goroutines{pod=~\"ephemeral-roles-.+\"}, \"instance\", \"\", \"instance\", \".+\")",
          "legendFormat": "{{pod}}",
          "refId": "A"
        }
      ],
      "thresholds": [
        {
          "$$hashKey": "object:683",
          "colorMode": "critical",
          "fill": false,
          "line": true,
          "op": "lt",
          "value": 100,
          "yaxis": "left"
        }
      ],
      "timeFrom": null,
      "timeRegions": [],
      "timeShift": null,
      "title": "Goroutines",
      "tooltip": {
        "shared": true,
        "sort": 2,
        "value_type": "individual"
      },
      "type": "graph",
      "xaxis": {
        "buckets": null,
        "mode": "time",
        "name": null,
        "show": true,
        "values": []
      },
      "yaxes": [
        {
          "$$hashKey": "object:670",
          "decimals": 0,
          "format": "short",
          "label": null,
          "logBase": 10,
          "max": "100",
          "min": null,
          "show": true
        },
        {
          "$$hashKey": "object:671",
          "format": "short",
          "label": null,
          "logBase": 1,
          "max": null,
          "min": null,
          "show": false
        }
      ],
      "yaxis": {
        "align": false,
        "alignLevel": null
      }
    },
    {
      "aliasColors": {},
      "bars": false,
      "dashLength": 10,
      "dashes": false,
      "datasource": "prometheus",
      "decimals": null,
      "fieldConfig": {
        "defaults": {
          "custom": {},
          "links": []
        },
        "overrides": []
      },
      "fill": 1,
      "fillGradient": 0,
      "gridPos": {
        "h": 11,
        "w": 12,
        "x": 0,
        "y": 36
      },
      "hiddenSeries": false,
      "id": 40,
      "legend": {
        "alignAsTable": true,
        "avg": true,
        "current": true,
        "max": false,
        "min": false,
        "show": true,
        "sort": "current",
        "sortDesc": true,
        "total": false,
        "values": true
      },
      "lines": true,
      "linewidth": 1,
      "links": [],
      "nullPointMode": "null",
      "percentage": false,
      "pluginVersion": "7.1.0",
      "pointradius": 5,
      "points": false,
      "renderer": "flot",
      "seriesOverrides": [
        {
          "alias": "/ephemeral-roles/",
          "color": "#1F60C4",
          "linewidth": 2
        }
      ],
      "spaceLength": 10,
      "stack": false,
      "steppedLine": false,
      "targets": [
        {
          "expr": "label_replace(go_memstats_heap_objects{pod=~\"ephemeral-roles-.+\"}, \"instance\", \"\", \"instance\", \".+\")",
          "legendFormat": "{{pod}}",
          "refId": "A"
        }
      ],
      "thresholds": [],
      "timeFrom": null,
      "timeRegions": [],
      "timeShift": null,
      "title": "Heap Objects",
      "tooltip": {
        "shared": true,
        "sort": 2,
        "value_type": "individual"
      },
      "type": "graph",
      "xaxis": {
        "buckets": null,
        "mode": "time",
        "name": null,
        "show": true,
        "values": []
      },
      "yaxes": [
        {
          "decimals": 0,
          "format": "short",
          "label": null,
          "logBase": 1,
          "max": null,
          "min": null,
          "show": true
        },
        {
          "format": "short",
          "label": null,
          "logBase": 1,
          "max": null,
          "min": null,
          "show": false
        }
      ],
      "yaxis": {
        "align": false,
        "alignLevel": null
      }
    },
    {
      "aliasColors": {},
      "bars": false,
      "dashLength": 10,
      "dashes": false,
      "datasource": "prometheus",
      "decimals": 2,
      "fieldConfig": {
        "defaults": {
          "custom": {},
          "links": []
        },
        "overrides": []
      },
      "fill": 1,
      "fillGradient": 0,
      "gridPos": {
        "h": 11,
        "w": 12,
        "x": 12,
        "y": 36
      },
      "hiddenSeries": false,
      "id": 18,
      "interval": "",
      "legend": {
        "alignAsTable": true,
        "avg": true,
        "current": true,
        "max": false,
        "min": false,
        "rightSide": false,
        "show": true,
        "sort": "current",
        "sortDesc": true,
        "total": false,
        "values": true
      },
      "lines": true,
      "linewidth": 1,
      "links": [],
      "nullPointMode": "null",
      "percentage": false,
      "pluginVersion": "7.1.0",
      "pointradius": 5,
      "points": false,
      "renderer": "flot",
      "seriesOverrides": [
        {
          "$$hashKey": "object:789",
          "alias": "/ephemeral-roles/",
          "color": "#E0B400",
          "linewidth": 2
        }
      ],
      "spaceLength": 10,
      "stack": false,
      "steppedLine": false,
      "targets": [
        {
          "expr": "label_replace(rate(process_cpu_seconds_total{pod=~\"ephemeral-roles-.+\"}[1m]), \"instance\", \"\", \"instance\", \".+\")",
          "legendFormat": "{{pod}}",
          "refId": "A"
        }
      ],
      "thresholds": [
        {
          "$$hashKey": "object:811",
          "colorMode": "critical",
          "fill": false,
          "line": true,
          "op": "lt",
          "value": 0.1,
          "yaxis": "left"
        }
      ],
      "timeFrom": null,
      "timeRegions": [],
      "timeShift": null,
      "title": "CPU Utilization",
      "tooltip": {
        "shared": true,
        "sort": 2,
        "value_type": "individual"
      },
      "type": "graph",
      "xaxis": {
        "buckets": null,
        "mode": "time",
        "name": null,
        "show": true,
        "values": []
      },
      "yaxes": [
        {
          "$$hashKey": "object:798",
          "decimals": 1,
          "format": "percentunit",
          "label": null,
          "logBase": 1,
          "max": ".10",
          "min": null,
          "show": true
        },
        {
          "$$hashKey": "object:799",
          "format": "short",
          "label": null,
          "logBase": 1,
          "max": null,
          "min": null,
          "show": false
        }
      ],
      "yaxis": {
        "align": false,
        "alignLevel": null
      }
    }
  ],
  "refresh": "5s",
  "schemaVersion": 26,
  "style": "dark",
  "tags": [],
  "templating": {
    "list": []
  },
  "time": {
    "from": "now-5m",
    "to": "now"
  },
  "timepicker": {
    "refresh_intervals": [
      "5s",
      "10s",
      "30s",
      "1m",
      "5m",
      "15m",
      "30m",
      "1h",
      "2h",
      "1d"
    ],
    "time_options": [
      "5m",
      "15m",
      "1h",
      "6h",
      "12h",
      "24h",
      "2d",
      "7d",
      "30d"
    ]
  },
  "timezone": "",
  "title": "Ephemeral Roles Metrics",
  "uid": "OqANQqtiz",
  "version": 2
}
